fleet_mcp/__init__.py
fleet_mcp/async_query_manager.py
fleet_mcp/cli.py
fleet_mcp/client.py
fleet_mcp/config.py
fleet_mcp/server.py
fleet_mcp/websocket_client.py
fleet_mcp/tools/__init__.py
fleet_mcp/tools/activity_tools.py
fleet_mcp/tools/async_query_tools.py
fleet_mcp/tools/carve_tools.py
fleet_mcp/tools/common.py
fleet_mcp/tools/config_tools.py
fleet_mcp/tools/custom_variable_tools.py
fleet_mcp/tools/device_tools.py
fleet_mcp/tools/host_tools.py
fleet_mcp/tools/invite_tools.py
fleet_mcp/tools/label_tools.py
fleet_mcp/tools/mdm_tools.py
fleet_mcp/tools/pack_tools.py
fleet_mcp/tools/policy_tools.py
fleet_mcp/tools/query_tools.py
fleet_mcp/tools/query_tools_readonly.py
fleet_mcp/tools/script_tools.py
fleet_mcp/tools/secret_tools.py
fleet_mcp/tools/software_tools.py
fleet_mcp/tools/table_discovery.py
fleet_mcp/tools/table_tools.py
fleet_mcp/tools/team_tools.py
fleet_mcp/tools/user_tools.py
fleet_mcp/tools/vpp_tools.py
fleet_mcp/utils/__init__.py
fleet_mcp/utils/host_identifier.py
fleet_mcp/utils/sql_validator.py
fleet_mcp-1.1.2.dist-info/METADATA
fleet_mcp-1.1.2.dist-info/WHEEL
fleet_mcp-1.1.2.dist-info/entry_points.txt
fleet_mcp-1.1.2.dist-info/licenses/LICENSE
fleet_mcp-1.1.2.dist-info/RECORD
