Metadata-Version: 2.4
Name: fleet-mcp
Version: 1.1.2
Summary: Model Context Protocol tool for Fleet DM integration
Project-URL: Homepage, https://github.com/SimplyMinimal/fleet-mcp
Project-URL: Repository, https://github.com/SimplyMinimal/fleet-mcp
Project-URL: Issues, https://github.com/SimplyMinimal/fleet-mcp/issues
Project-URL: Documentation, https://github.com/SimplyMinimal/fleet-mcp#readme
Author: SimplyMinimal
License: MIT
License-File: LICENSE
Keywords: device-management,fleet,mcp,osquery,security
Classifier: Development Status :: 3 - Alpha
Classifier: Intended Audience :: Developers
Classifier: License :: OSI Approved :: MIT License
Classifier: Programming Language :: Python :: 3
Classifier: Programming Language :: Python :: 3.10
Classifier: Programming Language :: Python :: 3.11
Classifier: Programming Language :: Python :: 3.12
Classifier: Topic :: Security
Classifier: Topic :: Software Development :: Libraries :: Python Modules
Classifier: Topic :: System :: Systems Administration
Requires-Python: >=3.10
Requires-Dist: click>=8.0.0
Requires-Dist: httpx>=0.25.0
Requires-Dist: mcp>=1.0.0
Requires-Dist: pydantic>=2.0.0
Requires-Dist: pyyaml>=6.0.0
Requires-Dist: typing-extensions>=4.0.0
Requires-Dist: websockets>=12.0
